{
  "global": {
    "test_id": 3,
    "name": "test name 3",
    "timeout": 56,
    "randomize": true
  },
  "candidate": {
    "time_start": 1660639552647,
    "firstname": "zxc",
    "lastname": "zxc",
    "contact": "zxc@gmail.com",
    "send_feedback": true,
    "feedback": "hehe"
  },
  "stats": { "time_start": 1660639552647, "time_end": 1660639580469 },
  "questions": [
    {
      "id": 7,
      "timeout": 17,
      "question": "Where do you went to school test name 3 8?",
      "multichoice": true,
      "topic": "Technical",
      "answers": ["32", "32", "33", "34", "35"],
      "history": [
        { "id": 0, "pos": 0, "timestamp": 1660639558347 },
        { "id": 1, "pos": 0, "timestamp": 1660639558710 },
        { "id": 2, "pos": 2, "timestamp": 1660639559008 },
        { "id": 3, "pos": 3, "timestamp": 1660639559274 },
        { "id": 4, "pos": 3, "timestamp": 1660639560793 },
        { "id": 5, "pos": 2, "timestamp": 1660639561053 },
        { "id": 6, "pos": 0, "timestamp": 1660639561314 },
        { "id": 7, "pos": 0, "timestamp": 1660639561813 }
      ],
      "results": [
        [
          { "answer": "32", "position": 0, "result": false },
          { "answer": "32", "position": 1, "result": false },
          { "answer": "33", "position": 2, "result": false },
          { "answer": "34", "position": 3, "result": false },
          { "answer": "35", "position": 4, "result": false }
        ]
      ],
      "completed": true,
      "clicks": 8
    },
    {
      "id": 1,
      "timeout": 4,
      "question": "Where do you went to school test name 3 2?",
      "multichoice": true,
      "topic": "Technical",
      "answers": ["1", "2", "3", "4", "5"],
      "history": [],
      "results": [
        [
          { "answer": "1", "position": 0, "result": false },
          { "answer": "2", "position": 1, "result": false },
          { "answer": "3", "position": 2, "result": false },
          { "answer": "4", "position": 3, "result": false },
          { "answer": "5", "position": 4, "result": false }
        ]
      ],
      "completed": false,
      "clicks": 0
    },
    {
      "id": 6,
      "timeout": 8,
      "question": "Where do you went to school test name 3 7?",
      "multichoice": true,
      "topic": "Technical",
      "answers": ["26", "27", "28", "29", "30"],
      "history": [],
      "results": [
        [
          { "answer": "26", "position": 0, "result": false },
          { "answer": "27", "position": 1, "result": false },
          { "answer": "28", "position": 2, "result": false },
          { "answer": "29", "position": 3, "result": false },
          { "answer": "30", "position": 4, "result": false }
        ]
      ],
      "completed": false,
      "clicks": 0
    },
    {
      "id": 4,
      "timeout": 6,
      "question": "Where do you went to school test name 3 5?",
      "multichoice": true,
      "topic": "Technical",
      "answers": ["16", "17", "18", "19", "20"],
      "history": [],
      "results": [
        [
          { "answer": "16", "position": 0, "result": false },
          { "answer": "17", "position": 1, "result": false },
          { "answer": "18", "position": 2, "result": false },
          { "answer": "19", "position": 3, "result": false },
          { "answer": "20", "position": 4, "result": false }
        ]
      ],
      "completed": false,
      "clicks": 0
    },
    {
      "id": 3,
      "timeout": 5,
      "question": "Where do you went to school test name 3 4?",
      "multichoice": true,
      "topic": "Technical",
      "answers": ["11", "12", "13", "14", "15"],
      "history": [],
      "results": [
        [
          { "answer": "11", "position": 0, "result": false },
          { "answer": "12", "position": 1, "result": false },
          { "answer": "13", "position": 2, "result": false },
          { "answer": "14", "position": 3, "result": false },
          { "answer": "15", "position": 4, "result": false }
        ]
      ],
      "completed": false,
      "clicks": 0
    },
    {
      "id": 5,
      "timeout": 7,
      "question": "Where do you went to school test name 3  6?",
      "multichoice": true,
      "topic": "Technical",
      "answers": ["21", "22", "23", "24", "25"],
      "history": [
        { "id": 0, "pos": 0, "timestamp": 1660639564839 },
        { "id": 1, "pos": 1, "timestamp": 1660639565098 },
        { "id": 2, "pos": 2, "timestamp": 1660639565373 },
        { "id": 3, "pos": 3, "timestamp": 1660639565682 },
        { "id": 4, "pos": 4, "timestamp": 1660639566081 },
        { "id": 5, "pos": 3, "timestamp": 1660639566311 },
        { "id": 6, "pos": 2, "timestamp": 1660639566578 },
        { "id": 7, "pos": 1, "timestamp": 1660639566828 },
        { "id": 8, "pos": 0, "timestamp": 1660639567062 },
        { "id": 9, "pos": 1, "timestamp": 1660639567395 },
        { "id": 10, "pos": 0, "timestamp": 1660639567702 }
      ],
      "results": [
        [
          { "answer": "21", "position": 0, "result": false },
          { "answer": "22", "position": 1, "result": false },
          { "answer": "23", "position": 2, "result": false },
          { "answer": "24", "position": 3, "result": false },
          { "answer": "25", "position": 4, "result": false }
        ]
      ],
      "completed": true,
      "clicks": 11
    },
    {
      "id": 0,
      "timeout": 3,
      "question": "What is your name test name 3 1?",
      "multichoice": false,
      "topic": "Softskills",
      "answers": ["Florian", "Sven", "Duy", "Minh", "Khoa"],
      "history": [{ "id": 0, "pos": 2, "timestamp": 1660639569549 }],
      "results": [
        [
          { "answer": "Florian", "position": 0, "result": false },
          { "answer": "Sven", "position": 1, "result": false },
          { "answer": "Duy", "position": 2, "result": false },
          { "answer": "Minh", "position": 3, "result": false },
          { "answer": "Khoa", "position": 4, "result": false }
        ]
      ],
      "completed": true,
      "clicks": 1
    }
  ]
}
